FastCopyFast/LICENSE
FastCopyFast/README.MD
FastCopyFast/__init__.py
FastCopyFast/requirements.txt
FastCopyFast/thirdparty.json
FastCopyFast-0.52.dist-info/LICENSE.rst
FastCopyFast-0.52.dist-info/METADATA
FastCopyFast-0.52.dist-info/WHEEL
FastCopyFast-0.52.dist-info/top_level.txt
FastCopyFast-0.52.dist-info/RECORD
