Metadata-Version: 2.1
Name: FastCopyFast
Version: 0.52
Summary: Three functions to copy/move files faster with Python
Home-page: https://github.com/hansalemaos/FastCopyFast
Author: Johannes Fischer
Author-email: <aulasparticularesdealemaosp@gmail.com>
License: MIT
Keywords: copy,file,faster
Classifier: Development Status :: 4 - Beta
Classifier: Programming Language :: Python :: 3 :: Only
Classifier: Programming Language :: Python :: 3.10
Classifier: Topic :: Scientific/Engineering :: Visualization
Classifier: Topic :: Software Development :: Libraries :: Python Modules
Classifier: Topic :: Utilities
License-File: LICENSE.rst
